pyexectime/__init__.py
pyexectime/inspector.py
pyexectime/pyexectime_test.py
pyexectime/version.py
PyExecTime-0.0.5.dist-info/LICENSE
PyExecTime-0.0.5.dist-info/METADATA
PyExecTime-0.0.5.dist-info/WHEEL
PyExecTime-0.0.5.dist-info/top_level.txt
PyExecTime-0.0.5.dist-info/RECORD
