Metadata-Version: 2.1
Name: PyExecTime
Version: 0.0.5
Summary: PyExecTime is a python module which can be used to find the execution time of a complete or partial python code.
Home-page: https://github.com/antaripchatterjee/PyExecTime
Author: Antarip Chatterjee
Author-email: antarip.chatterjee22@gmail.com
License: MIT
Platform: UNKNOWN
Classifier: License :: OSI Approved :: MIT License
Classifier: Operating System :: OS Independent
Classifier: Programming Language :: Python :: 3.5
Classifier: Environment :: Console
Classifier: Development Status :: 4 - Beta
Classifier: Intended Audience :: Developers
Classifier: Intended Audience :: Education
Classifier: Topic :: Education
Classifier: Topic :: Software Development
